setup.py
ext/jsmin.c
scripts/siteglass
siteglass/__init__.py
siteglass/amd.py
siteglass/builder.py
siteglass/config.py
siteglass/copy.py
siteglass/css.py
siteglass/data.py
siteglass/images.py
siteglass/js.py
siteglass/mergemin.py
siteglass.egg-info/PKG-INFO
siteglass.egg-info/SOURCES.txt
siteglass.egg-info/dependency_links.txt
siteglass.egg-info/requires.txt
siteglass.egg-info/top_level.txt
siteglass/data/almond.js