Metadata-Version: 1.1
Name: siteglass
Version: 0.2
Summary: A flexible tool for merging and compressing web assets.
Home-page: https://github.com/cooper-software/siteglass
Author: Cooper Software
Author-email: elisha@cooper.com
License: MIT
Download-URL: https://github.com/cooper-software/siteglass/tarball/master
Platform: UNKNOWN
Classifier: Development Status :: 4 - Beta
Classifier: Intended Audience :: Developers
Classifier: Environment :: Console
Classifier: Environment :: Web Environment
Classifier: License :: OSI Approved :: MIT License
Classifier: Topic :: Internet :: WWW/HTTP :: Dynamic Content
Classifier: Topic :: Software Development :: Pre-processors
Classifier: Topic :: Text Processing :: Filters
